{
 "actions": [],
 "allow_rename": 1,
 "creation": "2024-08-16 17:40:21.939145",
 "doctype": "DocType",
 "editable_grid": 1,
 "engine": "InnoDB",
 "field_order": [
  "offer",
  "type",
  "segment",
  "value",
  "starts_at",
  "ends_at"
 ],
 "fields": [
  {
   "fieldname": "offer",
   "fieldtype": "Link",
   "label": "Offer",
   "link_filters": "[[\"PL Offer\",\"active\",\"=\",1]]",
   "options": "PL Offer",
   "remember_last_selected_value": 1
  },
  {
   "fetch_from": "offer.value",
   "fetch_if_empty": 1,
   "fieldname": "value",
   "fieldtype": "Data",
   "label": "Value",
   "read_only": 1
  },
  {
   "fetch_from": "offer.type",
   "fetch_if_empty": 1,
   "fieldname": "type",
   "fieldtype": "Link",
   "label": "Type",
   "options": "PL Offer Type",
   "read_only": 1
  },
  {
   "fetch_from": "offer.segment",
   "fetch_if_empty": 1,
   "fieldname": "segment",
   "fieldtype": "Link",
   "label": "Segment",
   "options": "PL Offer Segment",
   "read_only": 1
  },
  {
   "fetch_from": "offer.startsat",
   "fetch_if_empty": 1,
   "fieldname": "starts_at",
   "fieldtype": "Datetime",
   "label": "Offer Starts At",
   "read_only": 1
  },
  {
   "fetch_from": "offer.endsat",
   "fetch_if_empty": 1,
   "fieldname": "ends_at",
   "fieldtype": "Datetime",
   "label": "Offer Ends At",
   "read_only": 1
  }
 ],
 "index_web_pages_for_search": 1,
 "istable": 1,
 "links": [],
 "modified": "2024-08-16 18:44:12.326909",
 "modified_by": "Administrator",
 "module": "Price List",
 "name": "PL Offer To DocType",
 "owner": "Administrator",
 "permissions": [],
 "sort_field": "creation",
 "sort_order": "DESC",
 "states": []
}